{
    "colour": [0, 255, 0],
    "ranges": [
        [0.5, "lower"],
        [1, "hills"]
    ],
    "lower": {
        "colour": [255, 255, 255],
        "altitude_surfaces": [
            [2, "sand"],
            [5, "grass"] ],
        "persistence": 0.85,
        "height_displacement": -12,
        "height_multiplier": 8
    },
    "hills": {
        "colour": [0, 0, 0],
        "altitude_surfaces": [
            [1, "grass"]
        ],
        "persistence": 0.9,
        "height_displacement": -12,
        "height_multiplier": 8
    }
}
